pdf_link_checker/__init__.py
pdf_link_checker/main.py
pdf_link_checker/pdf_link_check.py
pdf_link_checker/record.py
pdf_link_checker/utils.py
python_pdf_link_checker-1.1.10.dist-info/entry_points.txt
python_pdf_link_checker-1.1.10.dist-info/LICENSE
python_pdf_link_checker-1.1.10.dist-info/WHEEL
python_pdf_link_checker-1.1.10.dist-info/METADATA
python_pdf_link_checker-1.1.10.dist-info/RECORD
