Metadata-Version: 2.1
Name: python-pdf-link-checker
Version: 1.1.10
Summary: 
Home-page: https://github.com/pstoeckle/pdf-link-checker
License: MIT
Author: Matt Briggs
Author-email: mabrigg@microsoft.com
Maintainer: Patrick Stöckle
Maintainer-email: patrick.stoeckle@posteo.de
Requires-Python: >=3.7,<4.0
Classifier: License :: OSI Approved :: MIT License
Classifier: Programming Language :: Python :: 3
Classifier: Programming Language :: Python :: 3.7
Classifier: Programming Language :: Python :: 3.8
Classifier: Programming Language :: Python :: 3.9
Classifier: Programming Language :: Python :: 3.10
Classifier: Programming Language :: Python :: 3.11
Requires-Dist: PyPDF2 (>=1.26.0,<2.0.0)
Requires-Dist: requests (>=2.28.1,<3.0.0)
Requires-Dist: tqdm (>=4.64.1,<5.0.0)
Requires-Dist: typer (>=0.7.0,<0.8.0)
Project-URL: Repository, https://github.com/pstoeckle/pdf-link-checker
